[
    {
      "id": 1,
      "name": "Colar Pingente Mini-Cápsula com Meteorito Campo del Cielo",
      "value": 189.00,
      "imageUrl": "imagens/produto1.jpg"
    },

    {
      "id": 2,
      "name": "Meteorito Campo Del Cielo",
      "value": 60.00,
      "imageUrl": "imagens/produto2.jpg"
    },

    {
      "id": 3,
      "name": "Colar Pingente Cápsula com Meteorito Campo del Cielo",
      "value": 299.00,
      "imageUrl": "imagens/produto3.jpg"
    },

    {
      "id": 4,
      "name": "Meteorito Campo Del Cielo",
      "value": 80.00,
      "imageUrl": "imagens/produto4.jpg"
    },

    {
      "id": 5,
      "name": "Meteorito NWA 7977 - Acondrito Diogenito",
      "value": 70.00,
      "imageUrl": "imagens/produto5.jpg"
    },

    {
      "id": 6,
      "name": "Colar Pingente Mini-Cápsula / Meteorito NWA 7977",
      "value": 229.00,
      "imageUrl": "imagens/produto6.jpg"
    },

    {
      "id": 7,
      "name": "Meteorito Lunar NWA 11273 - Feldsp. Breccia",
      "value": 369.00,
      "imageUrl": "imagens/produto7.jpg"
    },

    {
      "id": 8,
      "name": "Meteorito Angra- 66g",
      "value": 70000.00,
      "imageUrl": "imagens/produto8.jpg"
    },

    {
      "id": 9,
      "name": "Pedra de impacto meteorito checo energia de cristal vidro natural",
      "value": 25000.0,
      "imageUrl": "imagens/produto9.jpg"
    },

    {
      "id": 10,
      "name": "Aerólito natural de Ferro300-400g quartzo cristal de quartzo",
      "value": 193.00,
      "imageUrl": "imagens/produto10.jpg"
    },

    {
      "id": 11,
      "name": "Raro natural  meteorito chinês de ferro magnético de alta frequência aerolite",
      "value": 1200.0,
      "imageUrl": "imagens/produto11.jpg"
    },

    {
      "id": 12,
      "name": "Coleção de pedras espaciais,  naturais de quatzo raro",
      "value": 159.00,
      "imageUrl": "imagens/produto12.jpg"
    }
  ]